{
  "Alabama": [
    { "city": "Birmingham", "lat": 33.5207, "lng": -86.8025 },
    { "city": "Montgomery", "lat": 32.3668, "lng": -86.3 },
    { "city": "Mobile", "lat": 30.6954, "lng": -88.0399 },
    { "city": "Huntsville", "lat": 34.7304, "lng": -86.5861 },
    { "city": "Tuscaloosa", "lat": 33.2098, "lng": -87.5692 },
    { "city": "Auburn", "lat": 32.6099, "lng": -85.4808 },
    { "city": "Dothan", "lat": 31.2232, "lng": -85.3905 },
    { "city": "Madison", "lat": 34.6993, "lng": -86.7483 },
    { "city": "Florence", "lat": 34.7998, "lng": -87.6773 },
    { "city": "Gadsden", "lat": 34.0143, "lng": -86.0063 }
  ],
  "Alaska": [
    { "city": "Anchorage", "lat": 61.2181, "lng": -149.9003 },
    { "city": "Fairbanks", "lat": 64.8378, "lng": -147.7164 },
    { "city": "Juneau", "lat": 58.3019, "lng": -134.4197 },
    { "city": "Sitka", "lat": 57.0531, "lng": -135.33 },
    { "city": "Ketchikan", "lat": 55.3422, "lng": -131.6461 },
    { "city": "Wasilla", "lat": 61.5814, "lng": -149.4394 },
    { "city": "Palmer", "lat": 61.5997, "lng": -149.1128 },
    { "city": "Kodiak", "lat": 57.79, "lng": -152.4072 },
    { "city": "Bethel", "lat": 60.7922, "lng": -161.7558 },
    { "city": "Nome", "lat": 64.5011, "lng": -165.4064 }
  ],
  "Arizona": [
    { "city": "Phoenix", "lat": 33.4484, "lng": -112.074 },
    { "city": "Tucson", "lat": 32.2226, "lng": -110.9747 },
    { "city": "Mesa", "lat": 33.4152, "lng": -111.8315 },
    { "city": "Chandler", "lat": 33.3061, "lng": -111.8413 },
    { "city": "Glendale", "lat": 33.5387, "lng": -112.186 },
    { "city": "Scottsdale", "lat": 33.4942, "lng": -111.9261 },
    { "city": "Gilbert", "lat": 33.3528, "lng": -111.789 },
    { "city": "Tempe", "lat": 33.4255, "lng": -111.94 },
    { "city": "Peoria", "lat": 33.5806, "lng": -112.2374 },
    { "city": "Surprise", "lat": 33.6292, "lng": -112.3679 },
    { "city": "Flagstaff", "lat": 35.1983, "lng": -111.6513 },
    { "city": "Yuma", "lat": 32.6927, "lng": -114.6277 },
    { "city": "Lake Havasu City", "lat": 34.4839, "lng": -114.3227 }
  ],
  "Arkansas": [
    { "city": "Little Rock", "lat": 34.7465, "lng": -92.2896 },
    { "city": "Fort Smith", "lat": 35.3859, "lng": -94.3985 },
    { "city": "Fayetteville", "lat": 36.0626, "lng": -94.1574 },
    { "city": "Springdale", "lat": 36.1867, "lng": -94.1288 },
    { "city": "Jonesboro", "lat": 35.8423, "lng": -90.7043 },
    { "city": "North Little Rock", "lat": 34.7695, "lng": -92.2671 },
    { "city": "Conway", "lat": 35.0887, "lng": -92.4421 },
    { "city": "Rogers", "lat": 36.332, "lng": -94.1185 },
    { "city": "Pine Bluff", "lat": 34.2284, "lng": -92.0032 },
    { "city": "Bentonville", "lat": 36.3729, "lng": -94.2088 },
    { "city": "Hot Springs", "lat": 34.5037, "lng": -93.0552 }
  ],
  "California": [
    { "city": "Los Angeles", "lat": 34.0522, "lng": -118.2437 },
    { "city": "San Francisco", "lat": 37.7749, "lng": -122.4194 },
    { "city": "San Diego", "lat": 32.7157, "lng": -117.1611 },
    { "city": "San Jose", "lat": 37.3382, "lng": -121.8863 },
    { "city": "Sacramento", "lat": 38.5816, "lng": -121.4944 },
    { "city": "Oakland", "lat": 37.8044, "lng": -122.2712 },
    { "city": "Long Beach", "lat": 33.7701, "lng": -118.1937 },
    { "city": "Fresno", "lat": 36.7378, "lng": -119.7871 },
    { "city": "Bakersfield", "lat": 35.3733, "lng": -119.0187 },
    { "city": "Anaheim", "lat": 33.8366, "lng": -117.9143 },
    { "city": "Santa Ana", "lat": 33.7455, "lng": -117.8677 },
    { "city": "Riverside", "lat": 33.9533, "lng": -117.3962 },
    { "city": "Stockton", "lat": 37.9577, "lng": -121.2908 },
    { "city": "Irvine", "lat": 33.6846, "lng": -117.8265 },
    { "city": "Chula Vista", "lat": 32.6401, "lng": -117.0842 },
    { "city": "Fremont", "lat": 37.5485, "lng": -121.9886 },
    { "city": "San Bernardino", "lat": 34.1083, "lng": -117.2898 },
    { "city": "Modesto", "lat": 37.6391, "lng": -120.9969 },
    { "city": "Fontana", "lat": 34.0922, "lng": -117.435 },
    { "city": "Oxnard", "lat": 34.1975, "lng": -119.1771 },
    { "city": "Huntington Beach", "lat": 33.6595, "lng": -117.9988 },
    { "city": "Glendale", "lat": 34.1425, "lng": -118.2551 },
    { "city": "Santa Clarita", "lat": 34.3917, "lng": -118.5426 },
    { "city": "Garden Grove", "lat": 33.7739, "lng": -117.9415 },
    { "city": "Oceanside", "lat": 33.1959, "lng": -117.3795 },
    { "city": "Rancho Cucamonga", "lat": 34.1064, "lng": -117.5931 },
    { "city": "Santa Rosa", "lat": 38.4404, "lng": -122.7144 },
    { "city": "Ontario", "lat": 34.0633, "lng": -117.6509 },
    { "city": "Lancaster", "lat": 34.6868, "lng": -118.1542 },
    { "city": "Elk Grove", "lat": 38.4088, "lng": -121.3716 },
    { "city": "Corona", "lat": 33.8753, "lng": -117.5664 },
    { "city": "Palmdale", "lat": 34.5794, "lng": -118.1165 },
    { "city": "Salinas", "lat": 36.6777, "lng": -121.6555 },
    { "city": "Pomona", "lat": 34.0552, "lng": -117.75 },
    { "city": "Hayward", "lat": 37.6688, "lng": -122.0808 },
    { "city": "Escondido", "lat": 33.1192, "lng": -117.0864 },
    { "city": "Torrance", "lat": 33.8358, "lng": -118.3406 },
    { "city": "Sunnyvale", "lat": 37.3688, "lng": -122.0363 },
    { "city": "Orange", "lat": 33.7879, "lng": -117.8531 },
    { "city": "Fullerton", "lat": 33.8703, "lng": -117.9242 },
    { "city": "Pasadena", "lat": 34.1478, "lng": -118.1445 }
  ],
  "Colorado": [
    { "city": "Denver", "lat": 39.7392, "lng": -104.9903 },
    { "city": "Colorado Springs", "lat": 38.8339, "lng": -104.8214 },
    { "city": "Aurora", "lat": 39.7294, "lng": -104.8319 },
    { "city": "Fort Collins", "lat": 40.5853, "lng": -105.0844 },
    { "city": "Lakewood", "lat": 39.7047, "lng": -105.0814 },
    { "city": "Thornton", "lat": 39.8681, "lng": -104.9722 },
    { "city": "Arvada", "lat": 39.8028, "lng": -105.0875 },
    { "city": "Westminster", "lat": 39.8367, "lng": -105.0372 },
    { "city": "Pueblo", "lat": 38.2544, "lng": -104.6091 },
    { "city": "Centennial", "lat": 39.5807, "lng": -104.8761 },
    { "city": "Boulder", "lat": 40.015, "lng": -105.2705 },
    { "city": "Greeley", "lat": 40.4233, "lng": -104.7091 },
    { "city": "Longmont", "lat": 40.1672, "lng": -105.1019 },
    { "city": "Loveland", "lat": 40.3978, "lng": -105.0748 },
    { "city": "Grand Junction", "lat": 39.0639, "lng": -108.5506 }
  ],
  "Connecticut": [
    { "city": "Bridgeport", "lat": 41.1865, "lng": -73.1952 },
    { "city": "New Haven", "lat": 41.3083, "lng": -72.9279 },
    { "city": "Hartford", "lat": 41.7658, "lng": -72.6734 },
    { "city": "Stamford", "lat": 41.0534, "lng": -73.5387 },
    { "city": "Waterbury", "lat": 41.5581, "lng": -73.0515 },
    { "city": "Norwalk", "lat": 41.1177, "lng": -73.4079 },
    { "city": "Danbury", "lat": 41.3948, "lng": -73.454 },
    { "city": "New Britain", "lat": 41.6612, "lng": -72.7795 },
    { "city": "West Hartford", "lat": 41.762, "lng": -72.742 },
    { "city": "Greenwich", "lat": 41.0262, "lng": -73.6282 },
    { "city": "Hamden", "lat": 41.3959, "lng": -72.9243 },
    { "city": "Meriden", "lat": 41.5381, "lng": -72.807 }
  ],
  "Delaware": [
    { "city": "Wilmington", "lat": 39.7391, "lng": -75.5398 },
    { "city": "Dover", "lat": 39.1612, "lng": -75.5264 },
    { "city": "Newark", "lat": 39.6837, "lng": -75.7497 },
    { "city": "Middletown", "lat": 39.4496, "lng": -75.7163 },
    { "city": "Bear", "lat": 39.6251, "lng": -75.6677 },
    { "city": "Glasgow", "lat": 39.6043, "lng": -75.7524 },
    { "city": "Brookside", "lat": 39.6568, "lng": -75.7299 },
    { "city": "Hockessin", "lat": 39.7868, "lng": -75.6918 },
    { "city": "Smyrna", "lat": 39.2998, "lng": -75.6055 },
    { "city": "Milford", "lat": 38.9126, "lng": -75.4277 }
  ],
  "Florida": [
    { "city": "Jacksonville", "lat": 30.3322, "lng": -81.6557 },
    { "city": "Miami", "lat": 25.7617, "lng": -80.1918 },
    { "city": "Tampa", "lat": 27.9506, "lng": -82.4572 },
    { "city": "Orlando", "lat": 28.5383, "lng": -81.3792 },
    { "city": "St. Petersburg", "lat": 27.7676, "lng": -82.6403 },
    { "city": "Hialeah", "lat": 25.8576, "lng": -80.2781 },
    { "city": "Tallahassee", "lat": 30.4518, "lng": -84.2807 },
    { "city": "Fort Lauderdale", "lat": 26.1224, "lng": -80.1373 },
    { "city": "Port St. Lucie", "lat": 27.273, "lng": -80.3582 },
    { "city": "Cape Coral", "lat": 26.5629, "lng": -81.9495 },
    { "city": "Pembroke Pines", "lat": 26.007, "lng": -80.2962 },
    { "city": "Hollywood", "lat": 26.0112, "lng": -80.1495 },
    { "city": "Miramar", "lat": 25.9873, "lng": -80.232 },
    { "city": "Gainesville", "lat": 29.6516, "lng": -82.3248 },
    { "city": "Coral Springs", "lat": 26.2712, "lng": -80.2706 },
    { "city": "Clearwater", "lat": 27.9659, "lng": -82.8001 },
    { "city": "Miami Gardens", "lat": 25.942, "lng": -80.2456 },
    { "city": "Brandon", "lat": 27.9378, "lng": -82.2859 },
    { "city": "West Palm Beach", "lat": 26.7153, "lng": -80.0534 },
    { "city": "Boca Raton", "lat": 26.3683, "lng": -80.1289 },
    { "city": "Sunrise", "lat": 26.1669, "lng": -80.2566 },
    { "city": "Plantation", "lat": 26.1267, "lng": -80.2331 },
    { "city": "Largo", "lat": 27.9095, "lng": -82.7873 },
    { "city": "Palm Bay", "lat": 28.0345, "lng": -80.5887 },
    { "city": "Melbourne", "lat": 28.0836, "lng": -80.6081 },
    { "city": "Pompano Beach", "lat": 26.2379, "lng": -80.1248 },
    { "city": "Davie", "lat": 26.0764, "lng": -80.2519 },
    { "city": "Fort Myers", "lat": 26.6406, "lng": -81.8723 },
    { "city": "Weston", "lat": 26.1003, "lng": -80.3997 },
    { "city": "Boynton Beach", "lat": 26.5318, "lng": -80.0928 }
  ],
  "Georgia": [
    { "city": "Atlanta", "lat": 33.749, "lng": -84.388 },
    { "city": "Augusta", "lat": 33.4735, "lng": -82.0105 },
    { "city": "Columbus", "lat": 32.4609, "lng": -84.9877 },
    { "city": "Macon", "lat": 32.8407, "lng": -83.6324 },
    { "city": "Savannah", "lat": 32.0835, "lng": -81.0998 },
    { "city": "Athens", "lat": 33.9519, "lng": -83.3576 },
    { "city": "Sandy Springs", "lat": 33.9304, "lng": -84.3733 },
    { "city": "Roswell", "lat": 34.0232, "lng": -84.3616 },
    { "city": "Johns Creek", "lat": 34.0289, "lng": -84.1986 },
    { "city": "Albany", "lat": 31.5804, "lng": -84.1557 },
    { "city": "Warner Robins", "lat": 32.613, "lng": -83.6241 },
    { "city": "Alpharetta", "lat": 34.0754, "lng": -84.2941 },
    { "city": "Marietta", "lat": 33.9526, "lng": -84.5499 },
    { "city": "Valdosta", "lat": 30.8327, "lng": -83.2785 },
    { "city": "Smyrna", "lat": 33.884, "lng": -84.5144 }
  ],
  "Hawaii": [
    { "city": "Honolulu", "lat": 21.3099, "lng": -157.8581 },
    { "city": "Pearl City", "lat": 21.3972, "lng": -157.9753 },
    { "city": "Hilo", "lat": 19.7297, "lng": -155.09 },
    { "city": "Kailua", "lat": 21.4022, "lng": -157.7394 },
    { "city": "Waipahu", "lat": 21.3861, "lng": -158.0089 },
    { "city": "Kaneohe", "lat": 21.418, "lng": -157.8025 },
    { "city": "Kailua-Kona", "lat": 19.64, "lng": -155.9969 },
    { "city": "Kahului", "lat": 20.8947, "lng": -156.47 },
    { "city": "Mililani Town", "lat": 21.4511, "lng": -158.015 },
    { "city": "Ewa Gentry", "lat": 21.3156, "lng": -158.0072 }
  ],
  "Idaho": [
    { "city": "Boise", "lat": 43.615, "lng": -116.2023 },
    { "city": "Nampa", "lat": 43.5407, "lng": -116.5635 },
    { "city": "Meridian", "lat": 43.6121, "lng": -116.3915 },
    { "city": "Idaho Falls", "lat": 43.4666, "lng": -112.034 },
    { "city": "Pocatello", "lat": 42.8713, "lng": -112.4455 },
    { "city": "Caldwell", "lat": 43.6629, "lng": -116.6874 },
    { "city": "Coeur d'Alene", "lat": 47.6777, "lng": -116.7804 },
    { "city": "Twin Falls", "lat": 42.563, "lng": -114.4609 },
    { "city": "Lewiston", "lat": 46.4165, "lng": -117.0177 },
    { "city": "Post Falls", "lat": 47.7179, "lng": -116.9515 }
  ],
  "Illinois": [
    { "city": "Chicago", "lat": 41.8781, "lng": -87.6298 },
    { "city": "Aurora", "lat": 41.7606, "lng": -88.3201 },
    { "city": "Rockford", "lat": 42.2711, "lng": -89.094 },
    { "city": "Joliet", "lat": 41.525, "lng": -88.0817 },
    { "city": "Naperville", "lat": 41.7508, "lng": -88.1535 },
    { "city": "Springfield", "lat": 39.7817, "lng": -89.6501 },
    { "city": "Peoria", "lat": 40.6936, "lng": -89.589 },
    { "city": "Elgin", "lat": 42.0354, "lng": -88.2826 },
    { "city": "Waukegan", "lat": 42.3637, "lng": -87.8448 },
    { "city": "Cicero", "lat": 41.8456, "lng": -87.7539 },
    { "city": "Champaign", "lat": 40.1164, "lng": -88.2434 },
    { "city": "Bloomington", "lat": 40.4842, "lng": -88.9937 },
    { "city": "Arlington Heights", "lat": 42.0883, "lng": -87.9806 },
    { "city": "Evanston", "lat": 42.0451, "lng": -87.6877 },
    { "city": "Schaumburg", "lat": 42.0334, "lng": -88.0834 },
    { "city": "Bolingbrook", "lat": 41.6986, "lng": -88.0684 },
    { "city": "Palatine", "lat": 42.1103, "lng": -88.0342 },
    { "city": "Skokie", "lat": 42.0334, "lng": -87.7334 },
    { "city": "Des Plaines", "lat": 42.0334, "lng": -87.8834 },
    { "city": "Orland Park", "lat": 41.6303, "lng": -87.8539 }
  ],
  "Indiana": [
    { "city": "Indianapolis", "lat": 39.7684, "lng": -86.1581 },
    { "city": "Fort Wayne", "lat": 41.0793, "lng": -85.1394 },
    { "city": "Evansville", "lat": 37.9716, "lng": -87.571 },
    { "city": "South Bend", "lat": 41.6764, "lng": -86.252 },
    { "city": "Carmel", "lat": 39.9784, "lng": -86.118 },
    { "city": "Fishers", "lat": 39.9568, "lng": -85.9685 },
    { "city": "Bloomington", "lat": 39.1653, "lng": -86.5264 },
    { "city": "Hammond", "lat": 41.5834, "lng": -87.5 },
    { "city": "Gary", "lat": 41.5868, "lng": -87.3464 },
    { "city": "Muncie", "lat": 40.1934, "lng": -85.3863 },
    { "city": "Lafayette", "lat": 40.4167, "lng": -86.8753 },
    { "city": "Terre Haute", "lat": 39.4667, "lng": -87.4139 },
    { "city": "Kokomo", "lat": 40.4864, "lng": -86.1336 },
    { "city": "Anderson", "lat": 40.1053, "lng": -85.6803 },
    { "city": "Noblesville", "lat": 40.0456, "lng": -86.0086 }
  ],
  "Iowa": [
    { "city": "Des Moines", "lat": 41.5868, "lng": -93.625 },
    { "city": "Cedar Rapids", "lat": 41.9778, "lng": -91.6656 },
    { "city": "Davenport", "lat": 41.5236, "lng": -90.5776 },
    { "city": "Sioux City", "lat": 42.4959, "lng": -96.4003 },
    { "city": "Waterloo", "lat": 42.4928, "lng": -92.3426 },
    { "city": "Iowa City", "lat": 41.6611, "lng": -91.5302 },
    { "city": "Council Bluffs", "lat": 41.2619, "lng": -95.8608 },
    { "city": "Ames", "lat": 42.0308, "lng": -93.6319 },
    { "city": "West Des Moines", "lat": 41.5772, "lng": -93.7114 },
    { "city": "Dubuque", "lat": 42.5006, "lng": -90.6648 },
    { "city": "Ankeny", "lat": 41.7297, "lng": -93.6058 },
    { "city": "Urbandale", "lat": 41.6267, "lng": -93.7121 },
    { "city": "Cedar Falls", "lat": 42.5347, "lng": -92.4453 },
    { "city": "Marion", "lat": 42.0347, "lng": -91.5979 }
  ],
  "Kansas": [
    { "city": "Wichita", "lat": 37.6872, "lng": -97.3301 },
    { "city": "Overland Park", "lat": 38.9822, "lng": -94.6708 },
    { "city": "Kansas City", "lat": 39.1142, "lng": -94.6275 },
    { "city": "Olathe", "lat": 38.8814, "lng": -94.8191 },
    { "city": "Topeka", "lat": 39.0473, "lng": -95.689 },
    { "city": "Lawrence", "lat": 38.9717, "lng": -95.2353 },
    { "city": "Shawnee", "lat": 39.0228, "lng": -94.7202 },
    { "city": "Manhattan", "lat": 39.1836, "lng": -96.5717 },
    { "city": "Lenexa", "lat": 38.9536, "lng": -94.7336 },
    { "city": "Salina", "lat": 38.8403, "lng": -97.6114 },
    { "city": "Hutchinson", "lat": 38.0608, "lng": -97.9297 },
    { "city": "Leavenworth", "lat": 39.3111, "lng": -94.9225 },
    { "city": "Leawood", "lat": 38.9667, "lng": -94.6169 },
    { "city": "Dodge City", "lat": 37.7528, "lng": -100.0171 }
  ],
  "Kentucky": [
    { "city": "Louisville", "lat": 38.2527, "lng": -85.7585 },
    { "city": "Lexington", "lat": 38.0406, "lng": -84.5037 },
    { "city": "Bowling Green", "lat": 36.9685, "lng": -86.4808 },
    { "city": "Owensboro", "lat": 37.7719, "lng": -87.1111 },
    { "city": "Covington", "lat": 39.0837, "lng": -84.5085 },
    { "city": "Richmond", "lat": 37.7479, "lng": -84.2946 },
    { "city": "Georgetown", "lat": 38.2098, "lng": -84.5588 },
    { "city": "Florence", "lat": 38.9989, "lng": -84.6266 },
    { "city": "Hopkinsville", "lat": 36.8656, "lng": -87.4886 },
    { "city": "Nicholasville", "lat": 37.8803, "lng": -84.573 },
    { "city": "Elizabethtown", "lat": 37.6948, "lng": -85.8591 },
    { "city": "Henderson", "lat": 37.8361, "lng": -87.5903 },
    { "city": "Frankfort", "lat": 38.2009, "lng": -84.8733 },
    { "city": "Jeffersontown", "lat": 38.1942, "lng": -85.5644 }
  ],
  "Louisiana": [
    { "city": "New Orleans", "lat": 29.9511, "lng": -90.0715 },
    { "city": "Baton Rouge", "lat": 30.4515, "lng": -91.1871 },
    { "city": "Shreveport", "lat": 32.5252, "lng": -93.7502 },
    { "city": "Lafayette", "lat": 30.2241, "lng": -92.0198 },
    { "city": "Lake Charles", "lat": 30.2266, "lng": -93.2174 },
    { "city": "Kenner", "lat": 29.994, "lng": -90.2417 },
    { "city": "Bossier City", "lat": 32.516, "lng": -93.7321 },
    { "city": "Monroe", "lat": 32.5093, "lng": -92.1193 },
    { "city": "Alexandria", "lat": 31.3112, "lng": -92.4426 },
    { "city": "Houma", "lat": 29.5958, "lng": -90.7195 },
    { "city": "Marrero", "lat": 29.8993, "lng": -90.1009 },
    { "city": "Bayou Cane", "lat": 29.6069, "lng": -90.7534 },
    { "city": "Prairieville", "lat": 30.2918, "lng": -90.9729 },
    { "city": "Central", "lat": 30.5513, "lng": -91.0345 }
  ],
  "Maine": [
    { "city": "Portland", "lat": 43.6591, "lng": -70.2568 },
    { "city": "Lewiston", "lat": 44.1004, "lng": -70.2148 },
    { "city": "Bangor", "lat": 44.8016, "lng": -68.7712 },
    { "city": "South Portland", "lat": 43.6414, "lng": -70.2409 },
    { "city": "Auburn", "lat": 44.0979, "lng": -70.2311 },
    { "city": "Biddeford", "lat": 43.4925, "lng": -70.4533 },
    { "city": "Sanford", "lat": 43.4395, "lng": -70.7739 },
    { "city": "Brunswick", "lat": 43.9142, "lng": -69.9653 },
    { "city": "Augusta", "lat": 44.3106, "lng": -69.7795 },
    { "city": "Scarborough", "lat": 43.5781, "lng": -70.3097 },
    { "city": "Gorham", "lat": 43.6795, "lng": -70.442 },
    { "city": "Westbrook", "lat": 43.677, "lng": -70.3712 }
  ],
  "Maryland": [
    { "city": "Baltimore", "lat": 39.2904, "lng": -76.6122 },
    { "city": "Frederick", "lat": 39.4143, "lng": -77.4105 },
    { "city": "Rockville", "lat": 39.084, "lng": -77.1528 },
    { "city": "Gaithersburg", "lat": 39.1434, "lng": -77.2014 },
    { "city": "Bowie", "lat": 38.9426, "lng": -76.7302 },
    { "city": "Hagerstown", "lat": 39.6417, "lng": -77.72 },
    { "city": "Annapolis", "lat": 38.9784, "lng": -76.4951 },
    { "city": "College Park", "lat": 38.9807, "lng": -76.9369 },
    { "city": "Salisbury", "lat": 38.3607, "lng": -75.5994 },
    { "city": "Laurel", "lat": 39.0993, "lng": -76.8483 },
    { "city": "Greenbelt", "lat": 38.9912, "lng": -76.8758 },
    { "city": "Cumberland", "lat": 39.6526, "lng": -78.7625 },
    { "city": "Westminster", "lat": 39.5751, "lng": -77.0003 },
    { "city": "Hyattsville", "lat": 38.9559, "lng": -76.9456 }
  ],
  "Massachusetts": [
    { "city": "Boston", "lat": 42.3601, "lng": -71.0589 },
    { "city": "Worcester", "lat": 42.2626, "lng": -71.8023 },
    { "city": "Springfield", "lat": 42.1015, "lng": -72.5898 },
    { "city": "Cambridge", "lat": 42.3736, "lng": -71.1097 },
    { "city": "Lowell", "lat": 42.6334, "lng": -71.3162 },
    { "city": "Brockton", "lat": 42.0834, "lng": -71.0184 },
    { "city": "Quincy", "lat": 42.2529, "lng": -71.0023 },
    { "city": "Lynn", "lat": 42.4668, "lng": -70.9495 },
    { "city": "Fall River", "lat": 41.7015, "lng": -71.155 },
    { "city": "Newton", "lat": 42.337, "lng": -71.2092 },
    { "city": "Lawrence", "lat": 42.707, "lng": -71.1631 },
    { "city": "Somerville", "lat": 42.3876, "lng": -71.0995 },
    { "city": "Waltham", "lat": 42.3765, "lng": -71.2356 },
    { "city": "Haverhill", "lat": 42.7762, "lng": -71.0773 },
    { "city": "Malden", "lat": 42.4251, "lng": -71.0662 },
    { "city": "Brookline", "lat": 42.3318, "lng": -71.1211 },
    { "city": "Plymouth", "lat": 41.9584, "lng": -70.6673 },
    { "city": "Medford", "lat": 42.4184, "lng": -71.1061 },
    { "city": "Taunton", "lat": 41.9001, "lng": -71.0897 },
    { "city": "Chicopee", "lat": 42.1487, "lng": -72.6081 }
  ],
  "Michigan": [
    { "city": "Detroit", "lat": 42.3314, "lng": -83.0458 },
    { "city": "Grand Rapids", "lat": 42.9634, "lng": -85.6681 },
    { "city": "Warren", "lat": 42.5144, "lng": -83.0146 },
    { "city": "Sterling Heights", "lat": 42.5803, "lng": -83.0302 },
    { "city": "Ann Arbor", "lat": 42.2808, "lng": -83.743 },
    { "city": "Lansing", "lat": 42.3314, "lng": -84.5467 },
    { "city": "Flint", "lat": 43.0125, "lng": -83.6875 },
    { "city": "Dearborn", "lat": 42.3223, "lng": -83.1763 },
    { "city": "Livonia", "lat": 42.3684, "lng": -83.3527 },
    { "city": "Westland", "lat": 42.3242, "lng": -83.4002 },
    { "city": "Troy", "lat": 42.6064, "lng": -83.1498 },
    { "city": "Farmington Hills", "lat": 42.4989, "lng": -83.3677 },
    { "city": "Kalamazoo", "lat": 42.2917, "lng": -85.5872 },
    { "city": "Wyoming", "lat": 42.9134, "lng": -85.7053 },
    { "city": "Southfield", "lat": 42.4734, "lng": -83.2219 },
    { "city": "Rochester Hills", "lat": 42.6583, "lng": -83.1499 },
    { "city": "Taylor", "lat": 42.2409, "lng": -83.2696 },
    { "city": "Pontiac", "lat": 42.6389, "lng": -83.291 },
    { "city": "St. Clair Shores", "lat": 42.4973, "lng": -82.8963 },
    { "city": "Royal Oak", "lat": 42.4895, "lng": -83.1446 }
  ],
  "Minnesota": [
    { "city": "Minneapolis", "lat": 44.9778, "lng": -93.265 },
    { "city": "Saint Paul", "lat": 44.9537, "lng": -93.09 },
    { "city": "Rochester", "lat": 44.0121, "lng": -92.4802 },
    { "city": "Bloomington", "lat": 44.8408, "lng": -93.2982 },
    { "city": "Duluth", "lat": 46.7867, "lng": -92.1005 },
    { "city": "Brooklyn Park", "lat": 45.0941, "lng": -93.3563 },
    { "city": "Plymouth", "lat": 45.0105, "lng": -93.4555 },
    { "city": "Saint Cloud", "lat": 45.5608, "lng": -94.1619 },
    { "city": "Eagan", "lat": 44.8041, "lng": -93.1668 },
    { "city": "Woodbury", "lat": 44.9239, "lng": -92.9594 },
    { "city": "Maple Grove", "lat": 45.0725, "lng": -93.4557 },
    { "city": "Eden Prairie", "lat": 44.8547, "lng": -93.4708 },
    { "city": "Coon Rapids", "lat": 45.12, "lng": -93.303 },
    { "city": "Burnsville", "lat": 44.7678, "lng": -93.2777 },
    { "city": "Blaine", "lat": 45.1607, "lng": -93.2349 }
  ],
  "Mississippi": [
    { "city": "Jackson", "lat": 32.2988, "lng": -90.1848 },
    { "city": "Gulfport", "lat": 30.3674, "lng": -89.0928 },
    { "city": "Southaven", "lat": 34.989, "lng": -90.0126 },
    { "city": "Hattiesburg", "lat": 31.3271, "lng": -89.2903 },
    { "city": "Biloxi", "lat": 30.396, "lng": -88.8853 },
    { "city": "Meridian", "lat": 32.3643, "lng": -88.7037 },
    { "city": "Tupelo", "lat": 34.2576, "lng": -88.7034 },
    { "city": "Greenville", "lat": 33.4035, "lng": -91.0612 },
    { "city": "Olive Branch", "lat": 34.9618, "lng": -89.8295 },
    { "city": "Horn Lake", "lat": 34.9551, "lng": -90.0374 },
    { "city": "Clinton", "lat": 32.3418, "lng": -90.3218 },
    { "city": "Pearl", "lat": 32.2746, "lng": -90.1312 },
    { "city": "Ridgeland", "lat": 32.4279, "lng": -90.1312 },
    { "city": "Starkville", "lat": 33.4504, "lng": -88.8184 }
  ],
  "Missouri": [
    { "city": "Kansas City", "lat": 39.0997, "lng": -94.5786 },
    { "city": "St. Louis", "lat": 38.627, "lng": -90.1994 },
    { "city": "Springfield", "lat": 37.2153, "lng": -93.2982 },
    { "city": "Independence", "lat": 39.0911, "lng": -94.4155 },
    { "city": "Columbia", "lat": 38.9517, "lng": -92.3341 },
    { "city": "Lee's Summit", "lat": 38.9109, "lng": -94.3822 },
    { "city": "O'Fallon", "lat": 38.8106, "lng": -90.6998 },
    { "city": "St. Joseph", "lat": 39.7391, "lng": -94.8469 },
    { "city": "St. Charles", "lat": 38.7881, "lng": -90.4974 },
    { "city": "St. Peters", "lat": 38.7874, "lng": -90.6298 },
    { "city": "Blue Springs", "lat": 39.0169, "lng": -94.2816 },
    { "city": "Florissant", "lat": 38.7892, "lng": -90.3223 },
    { "city": "Joplin", "lat": 37.0842, "lng": -94.5133 },
    { "city": "Chesterfield", "lat": 38.6631, "lng": -90.577 },
    { "city": "Jefferson City", "lat": 38.5767, "lng": -92.1735 }
  ],
  "Montana": [
    { "city": "Billings", "lat": 45.7833, "lng": -108.5007 },
    { "city": "Missoula", "lat": 46.8721, "lng": -113.994 },
    { "city": "Great Falls", "lat": 47.4941, "lng": -111.2833 },
    { "city": "Bozeman", "lat": 45.677, "lng": -111.0429 },
    { "city": "Butte", "lat": 46.0038, "lng": -112.5348 },
    { "city": "Helena", "lat": 46.5953, "lng": -112.0362 },
    { "city": "Kalispell", "lat": 48.1958, "lng": -114.3131 },
    { "city": "Havre", "lat": 48.55, "lng": -109.684 },
    { "city": "Anaconda", "lat": 46.1288, "lng": -112.9422 },
    { "city": "Miles City", "lat": 46.4083, "lng": -105.8406 }
  ],
  "Nebraska": [
    { "city": "Omaha", "lat": 41.2565, "lng": -95.9345 },
    { "city": "Lincoln", "lat": 40.8136, "lng": -96.7026 },
    { "city": "Bellevue", "lat": 41.137, "lng": -95.9145 },
    { "city": "Grand Island", "lat": 40.9264, "lng": -98.342 },
    { "city": "Kearney", "lat": 40.6994, "lng": -99.0817 },
    { "city": "Fremont", "lat": 41.4333, "lng": -96.4981 },
    { "city": "Hastings", "lat": 40.5861, "lng": -98.3887 },
    { "city": "North Platte", "lat": 41.1239, "lng": -100.7655 },
    { "city": "Norfolk", "lat": 42.0281, "lng": -97.417 },
    { "city": "Columbus", "lat": 41.43, "lng": -97.3686 }
  ],
  "Nevada": [
    { "city": "Las Vegas", "lat": 36.1699, "lng": -115.1398 },
    { "city": "Henderson", "lat": 36.0397, "lng": -114.9817 },
    { "city": "Reno", "lat": 39.5296, "lng": -119.8138 },
    { "city": "North Las Vegas", "lat": 36.1989, "lng": -115.1175 },
    { "city": "Sparks", "lat": 39.5349, "lng": -119.7527 },
    { "city": "Carson City", "lat": 39.1638, "lng": -119.7674 },
    { "city": "Fernley", "lat": 39.608, "lng": -119.2519 },
    { "city": "Elko", "lat": 40.8324, "lng": -115.7631 },
    { "city": "Mesquite", "lat": 36.8055, "lng": -114.0672 },
    { "city": "Boulder City", "lat": 35.9719, "lng": -114.8325 }
  ],
  "New Hampshire": [
    { "city": "Manchester", "lat": 42.9956, "lng": -71.4548 },
    { "city": "Nashua", "lat": 42.7654, "lng": -71.4676 },
    { "city": "Concord", "lat": 43.2081, "lng": -71.5376 },
    { "city": "Derry", "lat": 42.8806, "lng": -71.3273 },
    { "city": "Rochester", "lat": 43.3042, "lng": -70.9756 },
    { "city": "Salem", "lat": 42.7876, "lng": -71.2011 },
    { "city": "Dover", "lat": 43.1979, "lng": -70.8737 },
    { "city": "Merrimack", "lat": 42.8651, "lng": -71.4995 },
    { "city": "Londonderry", "lat": 42.8651, "lng": -71.374 },
    { "city": "Hudson", "lat": 42.7662, "lng": -71.434 },
    { "city": "Keene", "lat": 42.937, "lng": -72.2781 },
    { "city": "Portsmouth", "lat": 43.0718, "lng": -70.7626 }
  ],
  "New Jersey": [
    { "city": "Newark", "lat": 40.7357, "lng": -74.1724 },
    { "city": "Jersey City", "lat": 40.7178, "lng": -74.0431 },
    { "city": "Paterson", "lat": 40.9168, "lng": -74.1718 },
    { "city": "Elizabeth", "lat": 40.664, "lng": -74.2107 },
    { "city": "Edison", "lat": 40.5187, "lng": -74.4121 },
    { "city": "Woodbridge", "lat": 40.5576, "lng": -74.2847 },
    { "city": "Lakewood", "lat": 40.0979, "lng": -74.2176 },
    { "city": "Toms River", "lat": 39.9537, "lng": -74.1979 },
    { "city": "Hamilton", "lat": 40.2287, "lng": -74.6556 },
    { "city": "Trenton", "lat": 40.2206, "lng": -74.7565 },
    { "city": "Clifton", "lat": 40.8584, "lng": -74.1638 },
    { "city": "Camden", "lat": 39.9259, "lng": -75.1196 },
    { "city": "Brick", "lat": 40.0515, "lng": -74.1357 },
    { "city": "Cherry Hill", "lat": 39.9349, "lng": -75.0307 },
    { "city": "Passaic", "lat": 40.8568, "lng": -74.1284 },
    { "city": "Union City", "lat": 40.7662, "lng": -74.0235 },
    { "city": "Middletown", "lat": 40.3477, "lng": -74.0912 },
    { "city": "Gloucester", "lat": 39.8912, "lng": -75.1157 },
    { "city": "East Orange", "lat": 40.7673, "lng": -74.2049 },
    { "city": "Bayonne", "lat": 40.6687, "lng": -74.1143 }
  ],
  "New Mexico": [
    { "city": "Albuquerque", "lat": 35.0844, "lng": -106.6504 },
    { "city": "Las Cruces", "lat": 32.3199, "lng": -106.7637 },
    { "city": "Rio Rancho", "lat": 35.2328, "lng": -106.663 },
    { "city": "Santa Fe", "lat": 35.687, "lng": -105.9378 },
    { "city": "Roswell", "lat": 33.3943, "lng": -104.523 },
    { "city": "Farmington", "lat": 36.7281, "lng": -108.2187 },
    { "city": "Clovis", "lat": 34.4048, "lng": -103.2052 },
    { "city": "Hobbs", "lat": 32.7426, "lng": -103.136 },
    { "city": "Alamogordo", "lat": 32.8995, "lng": -105.9603 },
    { "city": "Carlsbad", "lat": 32.4206, "lng": -104.2288 }
  ],
  "New York": [
    { "city": "New York", "lat": 40.7128, "lng": -74.006 },
    { "city": "Buffalo", "lat": 42.8864, "lng": -78.8784 },
    { "city": "Rochester", "lat": 43.1566, "lng": -77.6088 },
    { "city": "Yonkers", "lat": 40.9312, "lng": -73.8988 },
    { "city": "Syracuse", "lat": 43.0481, "lng": -76.1474 },
    { "city": "Albany", "lat": 42.6526, "lng": -73.7562 },
    { "city": "New Rochelle", "lat": 40.9115, "lng": -73.7843 },
    { "city": "Mount Vernon", "lat": 40.9126, "lng": -73.837 },
    { "city": "Schenectady", "lat": 42.8142, "lng": -73.9396 },
    { "city": "Utica", "lat": 43.1009, "lng": -75.2327 },
    { "city": "White Plains", "lat": 41.034, "lng": -73.7629 },
    { "city": "Hempstead", "lat": 40.7062, "lng": -73.6187 },
    { "city": "Troy", "lat": 42.7284, "lng": -73.6918 },
    { "city": "Niagara Falls", "lat": 43.0962, "lng": -79.0377 },
    { "city": "Binghamton", "lat": 42.0987, "lng": -75.918 },
    { "city": "Freeport", "lat": 40.6576, "lng": -73.5832 },
    { "city": "Valley Stream", "lat": 40.6643, "lng": -73.7085 },
    { "city": "Long Beach", "lat": 40.5884, "lng": -73.6579 },
    { "city": "Rome", "lat": 43.2128, "lng": -75.4557 },
    { "city": "Ithaca", "lat": 42.443, "lng": -76.5019 }
  ],
  "North Carolina": [
    { "city": "Charlotte", "lat": 35.2271, "lng": -80.8431 },
    { "city": "Raleigh", "lat": 35.7796, "lng": -78.6382 },
    { "city": "Greensboro", "lat": 36.0726, "lng": -79.792 },
    { "city": "Durham", "lat": 35.994, "lng": -78.8986 },
    { "city": "Winston-Salem", "lat": 36.0999, "lng": -80.2442 },
    { "city": "Fayetteville", "lat": 35.0527, "lng": -78.8784 },
    { "city": "Cary", "lat": 35.7915, "lng": -78.7811 },
    { "city": "Wilmington", "lat": 34.2257, "lng": -77.9447 },
    { "city": "High Point", "lat": 35.9557, "lng": -80.0053 },
    { "city": "Greenville", "lat": 35.6127, "lng": -77.3663 },
    { "city": "Asheville", "lat": 35.5951, "lng": -82.5515 },
    { "city": "Concord", "lat": 35.4087, "lng": -80.5795 },
    { "city": "Gastonia", "lat": 35.2621, "lng": -81.1873 },
    { "city": "Jacksonville", "lat": 34.754, "lng": -77.4302 },
    { "city": "Chapel Hill", "lat": 35.9132, "lng": -79.0558 },
    { "city": "Rocky Mount", "lat": 35.9382, "lng": -77.7905 },
    { "city": "Burlington", "lat": 36.0957, "lng": -79.4378 },
    { "city": "Wilson", "lat": 35.7212, "lng": -77.9155 },
    { "city": "Huntersville", "lat": 35.4107, "lng": -80.8428 },
    { "city": "Kannapolis", "lat": 35.4871, "lng": -80.6217 }
  ],
  "North Dakota": [
    { "city": "Fargo", "lat": 46.8772, "lng": -96.7898 },
    { "city": "Bismarck", "lat": 46.8083, "lng": -100.7837 },
    { "city": "Grand Forks", "lat": 47.9253, "lng": -97.0329 },
    { "city": "Minot", "lat": 48.233, "lng": -101.2957 },
    { "city": "West Fargo", "lat": 46.8747, "lng": -96.9003 },
    { "city": "Williston", "lat": 48.147, "lng": -103.6183 },
    { "city": "Dickinson", "lat": 46.8792, "lng": -102.789 },
    { "city": "Mandan", "lat": 46.8267, "lng": -100.8896 },
    { "city": "Jamestown", "lat": 46.9105, "lng": -98.7084 },
    { "city": "Wahpeton", "lat": 46.2652, "lng": -96.6059 }
  ],
  "Ohio": [
    { "city": "Columbus", "lat": 39.9612, "lng": -82.9988 },
    { "city": "Cleveland", "lat": 41.4993, "lng": -81.6944 },
    { "city": "Cincinnati", "lat": 39.1031, "lng": -84.512 },
    { "city": "Toledo", "lat": 41.6528, "lng": -83.5379 },
    { "city": "Akron", "lat": 41.0814, "lng": -81.519 },
    { "city": "Dayton", "lat": 39.7589, "lng": -84.1916 },
    { "city": "Delaware", "lat": 40.2959, "lng": -83.0682 },
    { "city": "Parma", "lat": 41.4047, "lng": -81.7229 },
    { "city": "Canton", "lat": 40.7989, "lng": -81.3781 },
    { "city": "Youngstown", "lat": 41.0998, "lng": -80.6495 },
    { "city": "Lorain", "lat": 41.4528, "lng": -82.1823 },
    { "city": "Hamilton", "lat": 39.3995, "lng": -84.5613 },
    { "city": "Springfield", "lat": 39.9242, "lng": -83.8088 },
    { "city": "Kettering", "lat": 39.6895, "lng": -84.1688 },
    { "city": "Elyria", "lat": 41.3684, "lng": -82.1076 },
    { "city": "Lakewood", "lat": 41.482, "lng": -81.7982 },
    { "city": "Cuyahoga Falls", "lat": 41.1339, "lng": -81.4848 },
    { "city": "Middletown", "lat": 39.5151, "lng": -84.398 },
    { "city": "Newark", "lat": 40.0581, "lng": -82.4013 },
    { "city": "Mansfield", "lat": 40.7584, "lng": -82.5155 },
    { "city": "Mentor", "lat": 41.6662, "lng": -81.3395 },
    { "city": "Delaware", "lat": 40.2959, "lng": -83.0682 }
  ],
  "Oklahoma": [
    { "city": "Oklahoma City", "lat": 35.4676, "lng": -97.5164 },
    { "city": "Tulsa", "lat": 36.154, "lng": -95.9928 },
    { "city": "Norman", "lat": 35.2226, "lng": -97.4395 },
    { "city": "Broken Arrow", "lat": 36.0365, "lng": -95.7975 },
    { "city": "Lawton", "lat": 34.6087, "lng": -98.3959 },
    { "city": "Edmond", "lat": 35.6528, "lng": -97.4781 },
    { "city": "Moore", "lat": 35.3396, "lng": -97.4867 },
    { "city": "Midwest City", "lat": 35.4495, "lng": -97.3967 },
    { "city": "Enid", "lat": 36.3956, "lng": -97.8784 },
    { "city": "Stillwater", "lat": 36.1156, "lng": -97.0584 },
    { "city": "Muskogee", "lat": 35.7479, "lng": -95.3697 },
    { "city": "Bartlesville", "lat": 36.7473, "lng": -95.9808 },
    { "city": "Owasso", "lat": 36.2695, "lng": -95.8547 },
    { "city": "Shawnee", "lat": 35.3273, "lng": -96.9253 }
  ],
  "Oregon": [
    { "city": "Portland", "lat": 45.5152, "lng": -122.6784 },
    { "city": "Salem", "lat": 44.9429, "lng": -123.0351 },
    { "city": "Eugene", "lat": 44.0521, "lng": -123.0868 },
    { "city": "Gresham", "lat": 45.5001, "lng": -122.4302 },
    { "city": "Hillsboro", "lat": 45.5229, "lng": -122.989 },
    { "city": "Bend", "lat": 44.0582, "lng": -121.3153 },
    { "city": "Beaverton", "lat": 45.4871, "lng": -122.8037 },
    { "city": "Medford", "lat": 42.3265, "lng": -122.8756 },
    { "city": "Springfield", "lat": 44.0462, "lng": -123.022 },
    { "city": "Corvallis", "lat": 44.5646, "lng": -123.262 },
    { "city": "Albany", "lat": 44.6365, "lng": -123.1059 },
    { "city": "Tigard", "lat": 45.4312, "lng": -122.7715 },
    { "city": "Lake Oswego", "lat": 45.4207, "lng": -122.6707 },
    { "city": "Keizer", "lat": 44.9901, "lng": -123.0262 }
  ],
  "Pennsylvania": [
    { "city": "Philadelphia", "lat": 39.9526, "lng": -75.1652 },
    { "city": "Pittsburgh", "lat": 40.4406, "lng": -79.9959 },
    { "city": "Allentown", "lat": 40.6084, "lng": -75.4902 },
    { "city": "Erie", "lat": 42.1292, "lng": -80.0851 },
    { "city": "Reading", "lat": 40.3356, "lng": -75.9269 },
    { "city": "Scranton", "lat": 41.409, "lng": -75.6624 },
    { "city": "Bethlehem", "lat": 40.6259, "lng": -75.3705 },
    { "city": "Lancaster", "lat": 40.0379, "lng": -76.3055 },
    { "city": "Harrisburg", "lat": 40.2732, "lng": -76.8839 },
    { "city": "Altoona", "lat": 40.5187, "lng": -78.3947 },
    { "city": "York", "lat": 39.9626, "lng": -76.7277 },
    { "city": "State College", "lat": 40.7934, "lng": -77.86 },
    { "city": "Wilkes-Barre", "lat": 41.2459, "lng": -75.8813 },
    { "city": "Chester", "lat": 39.8498, "lng": -75.3557 },
    { "city": "Norristown", "lat": 40.1217, "lng": -75.3396 },
    { "city": "Johnstown", "lat": 40.3267, "lng": -78.922 },
    { "city": "Levittown", "lat": 40.1551, "lng": -74.8288 },
    { "city": "McKeesport", "lat": 40.3479, "lng": -79.8642 },
    { "city": "Easton", "lat": 40.6862, "lng": -75.221 },
    { "city": "New Castle", "lat": 41.0037, "lng": -80.347 }
  ],
  "Rhode Island": [
    { "city": "Providence", "lat": 41.824, "lng": -71.4128 },
    { "city": "Warwick", "lat": 41.7001, "lng": -71.4162 },
    { "city": "Cranston", "lat": 41.7798, "lng": -71.4373 },
    { "city": "Pawtucket", "lat": 41.8787, "lng": -71.3826 },
    { "city": "East Providence", "lat": 41.8137, "lng": -71.3701 },
    { "city": "Woonsocket", "lat": 42.0029, "lng": -71.5148 },
    { "city": "Newport", "lat": 41.4901, "lng": -71.3128 },
    { "city": "Central Falls", "lat": 41.8904, "lng": -71.3923 },
    { "city": "Westerly", "lat": 41.3776, "lng": -71.827 },
    { "city": "North Providence", "lat": 41.8551, "lng": -71.4662 }
  ],
  "South Carolina": [
    { "city": "Charleston", "lat": 32.7765, "lng": -79.9311 },
    { "city": "Columbia", "lat": 34.0007, "lng": -81.0348 },
    { "city": "North Charleston", "lat": 32.8546, "lng": -79.9748 },
    { "city": "Mount Pleasant", "lat": 32.8323, "lng": -79.8284 },
    { "city": "Rock Hill", "lat": 34.9249, "lng": -81.0251 },
    { "city": "Greenville", "lat": 34.8526, "lng": -82.394 },
    { "city": "Summerville", "lat": 33.0185, "lng": -80.1756 },
    { "city": "Sumter", "lat": 33.9204, "lng": -80.3414 },
    { "city": "Goose Creek", "lat": 32.981, "lng": -80.0326 },
    { "city": "Hilton Head Island", "lat": 32.2163, "lng": -80.7526 },
    { "city": "Florence", "lat": 34.1954, "lng": -79.7626 },
    { "city": "Spartanburg", "lat": 34.9496, "lng": -81.932 },
    { "city": "Anderson", "lat": 34.5037, "lng": -82.6501 },
    { "city": "Myrtle Beach", "lat": 33.6891, "lng": -78.8867 },
    { "city": "Greer", "lat": 34.9387, "lng": -82.227 }
  ],
  "South Dakota": [
    { "city": "Sioux Falls", "lat": 43.5446, "lng": -96.7311 },
    { "city": "Rapid City", "lat": 44.0805, "lng": -103.231 },
    { "city": "Aberdeen", "lat": 45.4647, "lng": -98.4865 },
    { "city": "Brookings", "lat": 44.3114, "lng": -96.7984 },
    { "city": "Watertown", "lat": 44.8997, "lng": -97.1142 },
    { "city": "Mitchell", "lat": 43.7094, "lng": -98.0298 },
    { "city": "Yankton", "lat": 42.8709, "lng": -97.3973 },
    { "city": "Pierre", "lat": 44.3683, "lng": -100.351 },
    { "city": "Huron", "lat": 44.3635, "lng": -98.2142 },
    { "city": "Vermillion", "lat": 42.7797, "lng": -96.9289 }
  ],
  "Tennessee": [
    { "city": "Memphis", "lat": 35.1495, "lng": -90.049 },
    { "city": "Nashville", "lat": 36.1627, "lng": -86.7816 },
    { "city": "Knoxville", "lat": 35.9606, "lng": -83.9207 },
    { "city": "Chattanooga", "lat": 35.0456, "lng": -85.3097 },
    { "city": "Clarksville", "lat": 36.5298, "lng": -87.3595 },
    { "city": "Murfreesboro", "lat": 35.8456, "lng": -86.3903 },
    { "city": "Franklin", "lat": 35.9251, "lng": -86.8689 },
    { "city": "Jackson", "lat": 35.6145, "lng": -88.814 },
    { "city": "Johnson City", "lat": 36.3134, "lng": -82.3535 },
    { "city": "Bartlett", "lat": 35.2045, "lng": -89.874 },
    { "city": "Hendersonville", "lat": 36.3048, "lng": -86.62 },
    { "city": "Kingsport", "lat": 36.5484, "lng": -82.5618 },
    { "city": "Collierville", "lat": 35.042, "lng": -89.6645 },
    { "city": "Cleveland", "lat": 35.1595, "lng": -84.8766 },
    { "city": "Smyrna", "lat": 35.9829, "lng": -86.5186 }
  ],
  "Texas": [
    { "city": "Houston", "lat": 29.7604, "lng": -95.3698 },
    { "city": "San Antonio", "lat": 29.4241, "lng": -98.4936 },
    { "city": "Dallas", "lat": 32.7767, "lng": -96.797 },
    { "city": "Austin", "lat": 30.2672, "lng": -97.7431 },
    { "city": "Fort Worth", "lat": 32.7555, "lng": -97.3308 },
    { "city": "El Paso", "lat": 31.7619, "lng": -106.485 },
    { "city": "Arlington", "lat": 32.7357, "lng": -97.1081 },
    { "city": "Corpus Christi", "lat": 27.8006, "lng": -97.3964 },
    { "city": "Plano", "lat": 33.0198, "lng": -96.6989 },
    { "city": "Laredo", "lat": 27.5306, "lng": -99.4803 },
    { "city": "Lubbock", "lat": 33.5779, "lng": -101.8552 },
    { "city": "Garland", "lat": 32.9126, "lng": -96.6389 },
    { "city": "Irving", "lat": 32.814, "lng": -96.9489 },
    { "city": "Amarillo", "lat": 35.222, "lng": -101.8313 },
    { "city": "Grand Prairie", "lat": 32.746, "lng": -96.9978 },
    { "city": "Brownsville", "lat": 25.9018, "lng": -97.4975 },
    { "city": "McKinney", "lat": 33.1972, "lng": -96.6397 },
    { "city": "Frisco", "lat": 33.1507, "lng": -96.8236 },
    { "city": "Pasadena", "lat": 29.6911, "lng": -95.2091 },
    { "city": "Killeen", "lat": 31.1171, "lng": -97.7278 },
    { "city": "Carrollton", "lat": 32.9537, "lng": -96.8903 },
    { "city": "Midland", "lat": 31.9974, "lng": -102.0779 },
    { "city": "Waco", "lat": 31.5494, "lng": -97.1467 },
    { "city": "Denton", "lat": 33.2148, "lng": -97.1331 },
    { "city": "Abilene", "lat": 32.4487, "lng": -99.7331 },
    { "city": "Beaumont", "lat": 30.086, "lng": -94.1018 },
    { "city": "Round Rock", "lat": 30.5083, "lng": -97.6789 },
    { "city": "Odessa", "lat": 31.8457, "lng": -102.3676 },
    { "city": "Wichita Falls", "lat": 33.9137, "lng": -98.4934 },
    { "city": "Richardson", "lat": 32.9483, "lng": -96.7299 }
  ],
  "Utah": [
    { "city": "Salt Lake City", "lat": 40.7608, "lng": -111.891 },
    { "city": "West Valley City", "lat": 40.6916, "lng": -112.0011 },
    { "city": "Provo", "lat": 40.2338, "lng": -111.6585 },
    { "city": "West Jordan", "lat": 40.6097, "lng": -111.9391 },
    { "city": "Orem", "lat": 40.2969, "lng": -111.6946 },
    { "city": "Sandy", "lat": 40.5649, "lng": -111.8389 },
    { "city": "Ogden", "lat": 41.223, "lng": -111.9738 },
    { "city": "St. George", "lat": 37.0965, "lng": -113.5684 },
    { "city": "Layton", "lat": 41.0602, "lng": -111.971 },
    { "city": "Taylorsville", "lat": 40.6677, "lng": -111.9388 },
    { "city": "South Jordan", "lat": 40.5621, "lng": -111.9296 },
    { "city": "Lehi", "lat": 40.3916, "lng": -111.8507 },
    { "city": "Logan", "lat": 41.737, "lng": -111.8338 },
    { "city": "Murray", "lat": 40.6669, "lng": -111.888 },
    { "city": "Draper", "lat": 40.5246, "lng": -111.8638 }
  ],
  "Vermont": [
    { "city": "Burlington", "lat": 44.4759, "lng": -73.2121 },
    { "city": "Essex", "lat": 44.4906, "lng": -73.1129 },
    { "city": "South Burlington", "lat": 44.4669, "lng": -73.1709 },
    { "city": "Colchester", "lat": 44.5269, "lng": -73.1312 },
    { "city": "Rutland", "lat": 43.6106, "lng": -72.9726 },
    { "city": "Bennington", "lat": 42.8781, "lng": -73.1956 },
    { "city": "Brattleboro", "lat": 42.8509, "lng": -72.5579 },
    { "city": "Milton", "lat": 44.6364, "lng": -73.1151 },
    { "city": "Hartford", "lat": 43.6478, "lng": -72.3278 },
    { "city": "Barre", "lat": 44.197, "lng": -72.502 },
    { "city": "Montpelier", "lat": 44.2601, "lng": -72.5806 },
    { "city": "St. Albans", "lat": 44.8106, "lng": -73.0818 }
  ],
  "Virginia": [
    { "city": "Virginia Beach", "lat": 36.8529, "lng": -75.978 },
    { "city": "Norfolk", "lat": 36.8468, "lng": -76.2852 },
    { "city": "Chesapeake", "lat": 36.7682, "lng": -76.2875 },
    { "city": "Richmond", "lat": 37.5407, "lng": -77.436 },
    { "city": "Newport News", "lat": 37.0871, "lng": -76.473 },
    { "city": "Alexandria", "lat": 38.8048, "lng": -77.0469 },
    { "city": "Hampton", "lat": 37.0298, "lng": -76.3452 },
    { "city": "Portsmouth", "lat": 36.8354, "lng": -76.2983 },
    { "city": "Suffolk", "lat": 36.7282, "lng": -76.5836 },
    { "city": "Roanoke", "lat": 37.271, "lng": -79.9414 },
    { "city": "Lynchburg", "lat": 37.4138, "lng": -79.1422 },
    { "city": "Harrisonburg", "lat": 38.4496, "lng": -78.8689 },
    { "city": "Leesburg", "lat": 39.1157, "lng": -77.5636 },
    { "city": "Charlottesville", "lat": 38.0293, "lng": -78.4767 },
    { "city": "Danville", "lat": 36.5859, "lng": -79.395 },
    { "city": "Blacksburg", "lat": 37.2296, "lng": -80.4139 },
    { "city": "Manassas", "lat": 38.7507, "lng": -77.4753 },
    { "city": "Petersburg", "lat": 37.2279, "lng": -77.4019 },
    { "city": "Fredericksburg", "lat": 38.3032, "lng": -77.4605 },
    { "city": "Winchester", "lat": 39.1857, "lng": -78.1633 }
  ],
  "Washington": [
    { "city": "Seattle", "lat": 47.6062, "lng": -122.3321 },
    { "city": "Spokane", "lat": 47.6587, "lng": -117.426 },
    { "city": "Tacoma", "lat": 47.2529, "lng": -122.4443 },
    { "city": "Vancouver", "lat": 45.6387, "lng": -122.6615 },
    { "city": "Bellevue", "lat": 47.6101, "lng": -122.2015 },
    { "city": "Kent", "lat": 47.3809, "lng": -122.2348 },
    { "city": "Everett", "lat": 47.979, "lng": -122.2021 },
    { "city": "Renton", "lat": 47.4829, "lng": -122.2171 },
    { "city": "Spokane Valley", "lat": 47.6732, "lng": -117.2394 },
    { "city": "Federal Way", "lat": 47.3223, "lng": -122.3126 },
    { "city": "Yakima", "lat": 46.6021, "lng": -120.5059 },
    { "city": "Bellingham", "lat": 48.7519, "lng": -122.4787 },
    { "city": "Kennewick", "lat": 46.2112, "lng": -119.1372 },
    { "city": "Auburn", "lat": 47.3073, "lng": -122.2284 },
    { "city": "Pasco", "lat": 46.2396, "lng": -119.1006 },
    { "city": "Marysville", "lat": 48.0518, "lng": -122.1771 },
    { "city": "Lakewood", "lat": 47.1717, "lng": -122.5185 },
    { "city": "Redmond", "lat": 47.674, "lng": -122.1215 },
    { "city": "Shoreline", "lat": 47.7556, "lng": -122.3415 },
    { "city": "Richland", "lat": 46.2857, "lng": -119.2845 }
  ],
  "West Virginia": [
    { "city": "Charleston", "lat": 38.3498, "lng": -81.6326 },
    { "city": "Huntington", "lat": 38.4192, "lng": -82.4452 },
    { "city": "Parkersburg", "lat": 39.2667, "lng": -81.5615 },
    { "city": "Morgantown", "lat": 39.6295, "lng": -79.9553 },
    { "city": "Wheeling", "lat": 40.064, "lng": -80.7209 },
    { "city": "Martinsburg", "lat": 39.4562, "lng": -77.9636 },
    { "city": "Fairmont", "lat": 39.4851, "lng": -80.1423 },
    { "city": "Beckley", "lat": 37.7782, "lng": -81.1882 },
    { "city": "Clarksburg", "lat": 39.2806, "lng": -80.3445 },
    { "city": "Lewisburg", "lat": 37.8018, "lng": -80.4456 }
  ],
  "Wisconsin": [
    { "city": "Milwaukee", "lat": 43.0389, "lng": -87.9065 },
    { "city": "Madison", "lat": 43.0731, "lng": -89.4012 },
    { "city": "Green Bay", "lat": 44.5133, "lng": -88.0133 },
    { "city": "Kenosha", "lat": 42.5847, "lng": -87.8212 },
    { "city": "Racine", "lat": 42.7261, "lng": -87.7829 },
    { "city": "Appleton", "lat": 44.2619, "lng": -88.4154 },
    { "city": "Waukesha", "lat": 43.0117, "lng": -88.2315 },
    { "city": "Eau Claire", "lat": 44.8113, "lng": -91.4985 },
    { "city": "Oshkosh", "lat": 44.0247, "lng": -88.5426 },
    { "city": "Janesville", "lat": 42.6828, "lng": -89.0187 },
    { "city": "West Allis", "lat": 43.0167, "lng": -88.007 },
    { "city": "La Crosse", "lat": 43.8014, "lng": -91.2396 },
    { "city": "Sheboygan", "lat": 43.7508, "lng": -87.7145 },
    { "city": "Wauwatosa", "lat": 43.0494, "lng": -88.0084 },
    { "city": "Fond du Lac", "lat": 43.773, "lng": -88.447 }
  ],
  "Wyoming": [
    { "city": "Cheyenne", "lat": 41.14, "lng": -104.8197 },
    { "city": "Casper", "lat": 42.8664, "lng": -106.3131 },
    { "city": "Laramie", "lat": 41.3114, "lng": -105.5911 },
    { "city": "Gillette", "lat": 44.2911, "lng": -105.5022 },
    { "city": "Rock Springs", "lat": 41.5875, "lng": -109.2029 },
    { "city": "Sheridan", "lat": 44.7975, "lng": -106.9561 },
    { "city": "Green River", "lat": 41.5286, "lng": -109.4662 },
    { "city": "Evanston", "lat": 41.2683, "lng": -111.0329 },
    { "city": "Riverton", "lat": 43.0642, "lng": -108.3801 },
    { "city": "Jackson", "lat": 43.4799, "lng": -110.7624 }
  ]
}
